pyulog/__init__.py
pyulog/_version.py
pyulog/core.py
pyulog/db.py
pyulog/extract_gps_dump.py
pyulog/info.py
pyulog/messages.py
pyulog/migrate_db.py
pyulog/params.py
pyulog/px4.py
pyulog/px4_events.py
pyulog/ulog2csv.py
pyulog/ulog2kml.py
pyulog/ulog2rosbag.py
pyulog/libevents_parse/__init__.py
pyulog/libevents_parse/health_and_arming_checks.py
pyulog/libevents_parse/parser.py
pyulog/sql/pyulog.1.sql
pyulog/sql/pyulog.2.sql
pyulog/sql/pyulog.3.sql
test/__init__.py
test/test_cli.py
test/test_db.py
test/test_migration.py
test/test_px4.py
test/test_px4_events.py
test/test_ulog.py
pyulog-1.1.0.dist-info/LICENSE.md
pyulog-1.1.0.dist-info/METADATA
pyulog-1.1.0.dist-info/WHEEL
pyulog-1.1.0.dist-info/entry_points.txt
pyulog-1.1.0.dist-info/top_level.txt
pyulog-1.1.0.dist-info/RECORD
